kag/__init__.py
kag/bin/__init__.py
kag/bin/base.py
kag/bin/kag_cmds.py
kag/bin/commands/__init__.py
kag/bin/commands/benchmark.py
kag/bin/commands/builder.py
kag/bin/commands/info.py
kag/bin/commands/mcp_server.py
kag/bridge/__init__.py
kag/bridge/spg_server_bridge.py
kag/builder/__init__.py
kag/builder/default_chain.py
kag/builder/main_builder.py
kag/builder/runner.py
kag/builder/component/__init__.py
kag/builder/component/aligner/__init__.py
kag/builder/component/aligner/kag_aligner.py
kag/builder/component/aligner/spg_aligner.py
kag/builder/component/external_graph/__init__.py
kag/builder/component/external_graph/external_graph.py
kag/builder/component/extractor/__init__.py
kag/builder/component/extractor/atomic_query_extractor.py
kag/builder/component/extractor/chunk_extractor.py
kag/builder/component/extractor/knowledge_unit_extractor.py
kag/builder/component/extractor/naive_rag_extractor.py
kag/builder/component/extractor/outline_extractor.py
kag/builder/component/extractor/schema_constraint_extractor.py
kag/builder/component/extractor/schema_free_extractor.py
kag/builder/component/extractor/summary_extractor.py
kag/builder/component/extractor/table_extractor.py
kag/builder/component/mapping/__init__.py
kag/builder/component/mapping/relation_mapping.py
kag/builder/component/mapping/spg_type_mapping.py
kag/builder/component/mapping/spo_mapping.py
kag/builder/component/postprocessor/__init__.py
kag/builder/component/postprocessor/kag_postprocessor.py
kag/builder/component/reader/__init__.py
kag/builder/component/reader/dict_reader.py
kag/builder/component/reader/docx_reader.py
kag/builder/component/reader/markdown_reader.py
kag/builder/component/reader/markdown_to_graph.py
kag/builder/component/reader/mix_reader.py
kag/builder/component/reader/mp_reader.py
kag/builder/component/reader/pdf_reader.py
kag/builder/component/reader/txt_reader.py
kag/builder/component/scanner/__init__.py
kag/builder/component/scanner/csv_scanner.py
openspg_kag-0.8.0.dist-info/licenses/LICENSE
openspg_kag-0.8.0.dist-info/METADATA
openspg_kag-0.8.0.dist-info/WHEEL
openspg_kag-0.8.0.dist-info/entry_points.txt
openspg_kag-0.8.0.dist-info/top_level.txt
openspg_kag-0.8.0.dist-info/RECORD
