Metadata-Version: 2.4
Name: openspg-kag
Version: 0.8.0
Summary: kag
Home-page: https://github.com/OpenSPG/openspg
Requires-Python: >=3.8
License-File: LICENSE
Requires-Dist: wget==3.2
Requires-Dist: pytest==7.4.2
Requires-Dist: json5
Requires-Dist: retrying==1.3.4
Requires-Dist: tabulate==0.9.0
Requires-Dist: jieba==0.42.1
Requires-Dist: nltk==3.8.1
Requires-Dist: tqdm==4.66.1
Requires-Dist: six==1.16.0
Requires-Dist: click==8.1.7
Requires-Dist: dateutils==0.6.12
Requires-Dist: certifi==2023.11.17
Requires-Dist: urllib3==1.26.16
Requires-Dist: python-dateutil==2.8.2
Requires-Dist: networkx==3.1
Requires-Dist: pydantic
Requires-Dist: requests==2.31.0
Requires-Dist: psutil
Requires-Dist: Jinja2>=3.0.3
Requires-Dist: cachetools==5.3.2
Requires-Dist: numpy>=1.23.1
Requires-Dist: pypdf
Requires-Dist: pandas
Requires-Dist: pycryptodome
Requires-Dist: markdown
Requires-Dist: bs4
Requires-Dist: protobuf==3.20.1
Requires-Dist: neo4j
Requires-Dist: dashscope
Requires-Dist: deprecated
Requires-Dist: schedule
Requires-Dist: openai
Requires-Dist: python-docx
Requires-Dist: charset_normalizer==3.3.2
Requires-Dist: pdfminer.six==20231228
Requires-Dist: ollama
Requires-Dist: tenacity
Requires-Dist: pyhocon
Requires-Dist: zodb
Requires-Dist: matplotlib
Requires-Dist: PyPDF2
Requires-Dist: ruamel.yaml
Requires-Dist: PyYAML
Requires-Dist: json_repair
Requires-Dist: gitpython
Requires-Dist: docstring_parser
Requires-Dist: aiolimiter
Requires-Dist: pyodps==0.12.2
Requires-Dist: aliyun-log-python-sdk==0.8.8
Requires-Dist: pyvis
Requires-Dist: aiofiles
Requires-Dist: mcp==1.6.0
Requires-Dist: httpx
Requires-Dist: diskcache
Requires-Dist: portalocker
Dynamic: home-page
Dynamic: license-file
Dynamic: requires-dist
Dynamic: requires-python
Dynamic: summary
